rforge/__init__.py
rforge/gui/data.py
rforge/gui/gui.py
rforge/gui/main_window.py
rforge/gui/common/adaptative_elements.py
rforge/gui/common/layer_information.py
rforge/gui/layers/import_layers.py
rforge/gui/layers/layers.py
rforge/gui/processes/process_panel.py
rforge/gui/processes/processes.py
rforge/gui/processes/panels/composites.py
rforge/gui/processes/panels/distance.py
rforge/gui/processes/panels/fuel.py
rforge/gui/processes/panels/height.py
rforge/gui/processes/panels/indices.py
rforge/gui/processes/panels/topography.py
rforge/gui/resources/resources.py
rforge/gui/viewer/save_operations.py
rforge/gui/viewer/viewer.py
rforge/library/containers/layer.py
rforge/library/containers/raster.py
rforge/library/processes/composite.py
rforge/library/processes/distance.py
rforge/library/processes/fuel.py
rforge/library/processes/height.py
rforge/library/processes/index.py
rforge/library/processes/topography.py
rforge/library/tools/data_validation.py
rforge/library/tools/exceptions.py
rforge/library/tools/rescale_dataset.py
raster_forge-0.6.1.dist-info/LICENSE
raster_forge-0.6.1.dist-info/METADATA
raster_forge-0.6.1.dist-info/WHEEL
raster_forge-0.6.1.dist-info/entry_points.txt
raster_forge-0.6.1.dist-info/top_level.txt
raster_forge-0.6.1.dist-info/RECORD
