Metadata-Version: 2.1
Name: raster-forge
Version: 0.6.1
Summary: Raster Forge is an package for the manipulation of raster data. It includes a library and a graphical user interface (GUI) application.
Author-email: Afonso Oliveira <afe.oliveira@campus.fct.unl.pt>
License: MIT
Keywords: raster, gui
Requires-Python: >=3.8
License-File: LICENSE
Requires-Dist: numpy
Requires-Dist: rasterio
Requires-Dist: spyndex
Requires-Dist: opencv-python
Requires-Dist: dask[dataframe]
Provides-Extra: devel
Requires-Dist: black ; extra == 'devel'
Requires-Dist: coverage ; extra == 'devel'
Requires-Dist: flake8 ; extra == 'devel'
Requires-Dist: flake8-black ; extra == 'devel'
Requires-Dist: flake8-builtins ; extra == 'devel'
Requires-Dist: flake8-bugbear ; extra == 'devel'
Requires-Dist: flake8-docstrings ; extra == 'devel'
Requires-Dist: flake8-isort ; extra == 'devel'
Requires-Dist: Flake8-pyproject ; extra == 'devel'
Requires-Dist: isort ; extra == 'devel'
Requires-Dist: pre-commit ; extra == 'devel'
Requires-Dist: pytest >=7.0.0 ; extra == 'devel'
Requires-Dist: pytest-cov ; extra == 'devel'
Requires-Dist: pytest-qt ; extra == 'devel'
Requires-Dist: Sphinx ; extra == 'devel'
Requires-Dist: sphinx-design ; extra == 'devel'
Requires-Dist: pydata-sphinx-theme ; extra == 'devel'
Provides-Extra: gui
Requires-Dist: matplotlib ; extra == 'gui'
Requires-Dist: PySide6 ; extra == 'gui'
